<Properties StartupConfiguration="{AF31347B-018E-4D4B-8489-592B7A4FF86D}|Default">
  <MonoDevelop.Ide.Workbench ActiveDocument="GymLedgerAPI/Controllers/CategoryController.cs">
    <Files>
      <File FileName="GymLedgerAPI/Controllers/ExerciseController.cs" Line="157" Column="1" />
      <File FileName="GymLedgerAPI/Domain/Models/Training.cs" Line="94" Column="1" />
      <File FileName="GymLedgerAPI/Controllers/ExerciseEvaulationController.cs" Line="17" Column="63" />
      <File FileName="GymLedgerAPI/Controllers/TrainingController.cs" Line="145" Column="1" />
      <File FileName="GymLedgerAPI/Data/Repositories/TrainingRepo.cs" Line="58" Column="1" />
      <File FileName="GymLedgerAPI/Domain/Interfaces /IExerciseRepo.cs" />
      <File FileName="GymLedgerAPI/Domain/Interfaces /IGymnastRepo.cs" />
      <File FileName="GymLedgerAPI/Data/Repositories/ExerciseRepo.cs" Line="49" Column="1" />
      <File FileName="GymLedgerAPI/Domain/Models/ExerciseEvaluation.cs" Line="68" Column="1" />
      <File FileName="GymLedgerAPI/Domain/Models/Exercise.cs" Line="12" Column="1" />
      <File FileName="GymLedgerAPI/Data/ApplicationDbContext.cs" Line="42" Column="1" />
      <File FileName="GymLedgerAPI/Data/DataInit.cs" Line="183" Column="1" />
      <File FileName="GymLedgerAPI/Domain/Models/Gymnast.cs" Line="47" Column="1" />
      <File FileName="GymLedgerAPI/Domain/Models/Category.cs" Line="16" Column="1" />
      <File FileName="GymLedgerAPI/Data/Mapping/ExerciseEvaluationMapper.cs" Line="18" Column="1" />
      <File FileName="GymLedgerAPI/Data/Mapping/TrainingMapper.cs" Line="24" Column="1" />
      <File FileName="GymLedgerAPI/Data/Repositories/ExerciseEvaluationRepo.cs" Line="59" Column="1" />
      <File FileName="GymLedgerAPI/Domain/Interfaces /IExerciseEvaluationRepo.cs" Line="13" Column="1" />
      <File FileName="GymLedgerAPI/Controllers/GymnastController.cs" Line="86" Column="1" />
      <File FileName="GymLedgerAPI/Domain/DTOs/EvaluatieDTO.cs" Line="26" Column="1" />
      <File FileName="GymLedgerAPI/Domain/Models/Coach.cs" Line="1" Column="1" />
      <File FileName="GymLedgerAPI/Domain/Models/DCD.cd" Line="1" Column="1" />
      <File FileName="GymLedgerAPI/Controllers/CategoryController.cs" Line="1" Column="1" />
      <File FileName="GymLedgerAPI/Controllers/AccountController.cs" Line="1" Column="1" />
    </Files>
    <Pads>
      <Pad Id="ProjectPad">
        <State name="__root__">
          <Node name="GymLedgerAPI" expanded="True">
            <Node name="GymLedgerAPI" expanded="True">
              <Node name="Dependencies" expanded="True" />
              <Node name="Controllers" expanded="True">
                <Node name="CategoryController.cs" selected="True" />
              </Node>
              <Node name="Data" expanded="True">
                <Node name="Repositories" expanded="True" />
              </Node>
              <Node name="Domain" expanded="True">
                <Node name="DTOs" expanded="True" />
                <Node name="Interfaces " expanded="True" />
                <Node name="Models" expanded="True" />
              </Node>
            </Node>
          </Node>
        </State>
      </Pad>
    </Pads>
  </MonoDevelop.Ide.Workbench>
  <MonoDevelop.Ide.DebuggingService.PinnedWatches />
  <MonoDevelop.Ide.Workspace ActiveConfiguration="Debug" />
  <MonoDevelop.Ide.ItemProperties.GymLedgerAPI PreferredExecutionTarget="/Applications/Safari.app" />
  <MonoDevelop.Ide.DebuggingService.Breakpoints>
    <BreakpointStore>
      <Breakpoint file="/Users/florianlanduyt/Documents/TIN/Semester 2 /Webapps /Backend /GymLedgerAPI/GymLedgerAPI/Domain/DTOs/lqe45rxf.fy1~" relfile="GymLedgerAPI/Domain/DTOs/lqe45rxf.fy1~" line="80" column="1" />
      <Breakpoint file="/Users/florianlanduyt/Documents/TIN/Semester 2 /Webapps /Backend /GymLedgerAPI/GymLedgerAPI/Domain/DTOs/4vg13pxb.8jp~" relfile="GymLedgerAPI/Domain/DTOs/4vg13pxb.8jp~" line="43" column="1" />
    </BreakpointStore>
  </MonoDevelop.Ide.DebuggingService.Breakpoints>
  <MultiItemStartupConfigurations />
</Properties>